{
  "tableName": "LG_CVARPASG",
  "displayName": "CVARPASG",
  "description": "",
  "category": "Sistem",
  "type": "program-independent",
  "placeholders": [],
  "indexes": [
    {
      "no": 1,
      "name": "CVARPASG_I1",
      "type": "CLUSTERED",
      "isPrimaryKey": true,
      "isUnique": true,
      "fields": [
        "LOGICALREF"
      ]
    },
    {
      "no": 2,
      "name": "CVARPASG_I2",
      "type": "NONCLUSTERED",
      "isPrimaryKey": false,
      "isUnique": true,
      "fields": [
        "CSTVNDREF",
        "FIRMNO",
        "ARPREF"
      ]
    }
  ],
  "fields": [
    {
      "name": "LOGICALREF",
      "type": "int",
      "description": "\r"
    },
    {
      "name": "CSTVNDREF",
      "type": "int",
      "description": "\r"
    },
    {
      "name": "ARPREF",
      "type": "int",
      "description": "\r"
    },
    {
      "name": "FIRMNO",
      "type": "smallint",
      "description": "\r"
    },
    {
      "name": "SITEID",
      "type": "smallint",
      "description": "\r"
    },
    {
      "name": "RECSTATUS",
      "type": "smallint",
      "description": "\r"
    },
    {
      "name": "ORGLOGICREF",
      "type": "int",
      "description": "\r"
    },
    {
      "name": "DEFAULTFLG",
      "type": "smallint",
      "description": "\r"
    }
  ],
  "commonQueries": [],
  "indexCount": 2
}